{"name":"T2 or T3 Halberd Trench Designs","faction":"w","projectSettings":{"showProductionIcons":true,"showRangeWhenSelected":true,"ranges":{"crane":false,"radio":false,"killbox":false,"killboxMG":false,"killboxAT":false,"killboxArty":false,"preventDecay":false}},"entities":[{"id":0,"x":1774.621212121212,"y":-2092.80303030303,"type":"building","subtype":"fortt2","sortOffset":73,"connections":{"1":{"4":3},"2":{"7":0},"3":{"3":0}}},{"id":1,"x":1557.7651515151515,"y":-1875.9469696969695,"type":"building","subtype":"fortt2_atgunait2","sortOffset":51,"connections":{"0":{"6":3}}},{"id":2,"x":1991.4772727272725,"y":-1875.9469696969695,"type":"building","subtype":"fortt2_atgunait2","sortOffset":51,"connections":{"0":{"5":0}}},{"id":3,"x":1614.5833333333333,"y":-2092.80303030303,"rotation":1.5707963267948961,"type":"building","subtype":"fortcornert2","sortOffset":73,"connections":{"0":{"0":3},"6":{"6":6}}},{"id":4,"x":1934.6590909090908,"y":-2092.80303030303,"type":"building","subtype":"fortcornert2","sortOffset":73,"connections":{"3":{"0":1},"6":{"5":6}}},{"id":5,"x":1991.4772727272725,"y":-2035.9848484848485,"rotation":3.141592653589793,"type":"building","subtype":"fortcornert2","sortOffset":73,"connections":{"0":{"2":0},"3":{"9":3},"6":{"4":6}}},{"id":6,"x":1557.7651515151515,"y":-2035.9848484848485,"rotation":-1.570796326794897,"type":"building","subtype":"fortcornert2","sortOffset":73,"connections":{"0":{"8":1},"3":{"1":0},"6":{"3":6}}},{"id":7,"x":1774.621212121212,"y":-1932.7651515151515,"rotation":-4.440892098500626e-16,"type":"building","subtype":"fortt2_mgait2","sortOffset":51,"connections":{"0":{"0":2},"2":{"14":2}}},{"id":8,"x":1397.7272727272727,"y":-2035.9848484848485,"type":"building","subtype":"fortt2_rifleait2","sortOffset":51,"connections":{"1":{"6":0},"2":{"10":2}}},{"id":9,"x":2151.5151515151515,"y":-2035.9848484848485,"type":"building","subtype":"fortt2_rifleait2","sortOffset":51,"connections":{"2":{"11":2},"3":{"5":3}}},{"id":10,"x":1397.7272727272727,"y":-1796.401515151515,"rotation":-1.5707963267948966,"type":"building","subtype":"trencht2","sortOffset":188,"connections":{"0":{"12":1},"2":{"8":2}}},{"id":11,"x":2151.5151515151515,"y":-1796.401515151515,"rotation":-1.570796326794897,"type":"building","subtype":"trencht2","sortOffset":188,"connections":{"0":{"13":1},"2":{"9":2}}},{"id":12,"x":1397.7272727272727,"y":-1589.0151515151515,"type":"building","subtype":"trencht2","sortOffset":188,"connections":{"0":{"31":2},"1":{"10":0},"2":{"15":0}}},{"id":13,"x":2151.5151515151515,"y":-1589.0151515151515,"type":"building","subtype":"trencht2","sortOffset":188,"connections":{"0":{"16":1},"1":{"11":0}}},{"id":14,"x":1774.621212121212,"y":-1693.181818181818,"rotation":-1.570796326794897,"type":"building","subtype":"trencht2","sortOffset":188,"connections":{"1":{"15":1},"2":{"7":2},"3":{"16":0}}},{"id":15,"x":1557.7651515151515,"y":-1589.0151515151515,"rotation":-4.440892098500626e-16,"type":"building","subtype":"trenchconnectort2","sortOffset":188,"railPoints":[{"x":0,"y":0,"rotation":3.141592653589793},{"x":169.92424242424204,"y":-104.16666666666653,"rotation":3.141592653589793}],"connections":{"0":{"12":2},"1":{"14":1}}},{"id":16,"x":1821.969696969697,"y":-1693.181818181818,"type":"building","subtype":"trenchconnectort2","sortOffset":188,"railPoints":[{"x":0,"y":0,"rotation":3.141592653589793},{"x":169.9242424242416,"y":104.16666666666656,"rotation":3.141592653589793}],"connections":{"0":{"14":3},"1":{"13":0}}},{"id":17,"x":3.652460061071268,"y":-1589.150570241958,"rotation":8.881784197001252e-16,"type":"building","subtype":"trenchempt2","sortOffset":188,"connections":{"2":{"30":0},"7":{"139":2}}},{"id":18,"x":700.7575757575758,"y":-2092.80303030303,"rotation":8.881784197001252e-16,"type":"building","subtype":"fortt2","sortOffset":73,"connections":{"1":{"22":3},"2":{"25":0},"3":{"21":0}}},{"id":19,"x":483.9015151515151,"y":-1875.9469696969695,"rotation":8.881784197001252e-16,"type":"building","subtype":"fortt2_atgunait2","sortOffset":51,"connections":{"0":{"24":3}}},{"id":20,"x":917.6136363636364,"y":-1875.9469696969695,"rotation":4.440892098500626e-16,"type":"building","subtype":"fortt2_atgunait2","sortOffset":51,"connections":{"0":{"23":0}}},{"id":21,"x":540.719696969697,"y":-2092.80303030303,"rotation":1.5707963267948974,"type":"building","subtype":"fortcornert2","sortOffset":73,"connections":{"0":{"18":3},"6":{"24":6}}},{"id":22,"x":860.7954545454545,"y":-2092.80303030303,"rotation":8.881784197001252e-16,"type":"building","subtype":"fortcornert2","sortOffset":73,"connections":{"3":{"18":1},"6":{"23":6}}},{"id":23,"x":917.6136363636364,"y":-2035.9848484848485,"rotation":-3.1415926535897927,"type":"building","subtype":"fortcornert2","sortOffset":73,"connections":{"0":{"20":0},"3":{"27":3},"6":{"22":6}}},{"id":24,"x":483.9015151515151,"y":-2035.9848484848485,"rotation":-1.570796326794896,"type":"building","subtype":"fortcornert2","sortOffset":73,"connections":{"0":{"26":1},"3":{"19":0},"6":{"21":6}}},{"id":25,"x":700.7575757575758,"y":-1932.7651515151515,"rotation":-4.440892098500626e-16,"type":"building","subtype":"fortt2_mgait2","sortOffset":51,"connections":{"0":{"18":2},"2":{"32":2}}},{"id":26,"x":323.8636363636364,"y":-2035.9848484848485,"rotation":8.881784197001252e-16,"type":"building","subtype":"fortt2_rifleait2","sortOffset":51,"connections":{"1":{"24":0},"2":{"28":2}}},{"id":27,"x":1077.651515151515,"y":-2035.9848484848485,"type":"building","subtype":"fortt2_rifleait2","sortOffset":51,"connections":{"2":{"29":2},"3":{"23":3}}},{"id":28,"x":323.8636363636364,"y":-1796.401515151515,"rotation":-1.5707963267948957,"type":"building","subtype":"trencht2","sortOffset":188,"connections":{"0":{"30":1},"2":{"26":2}}},{"id":29,"x":1077.651515151515,"y":-1796.401515151515,"rotation":-1.570796326794897,"type":"building","subtype":"trencht2","sortOffset":188,"connections":{"0":{"31":1},"2":{"27":2}}},{"id":30,"x":323.8636363636364,"y":-1589.0151515151515,"rotation":8.881784197001252e-16,"type":"building","subtype":"trencht2","sortOffset":188,"connections":{"0":{"17":2},"1":{"28":0},"2":{"33":0}}},{"id":31,"x":1077.651515151515,"y":-1589.0151515151515,"type":"building","subtype":"trencht2","sortOffset":188,"connections":{"0":{"34":1},"1":{"29":0},"2":{"12":0}}},{"id":32,"x":700.7575757575758,"y":-1693.181818181818,"rotation":-1.570796326794897,"type":"building","subtype":"trencht2","sortOffset":188,"connections":{"1":{"33":1},"2":{"25":2},"3":{"34":0}}},{"id":33,"x":483.9015151515151,"y":-1589.0151515151515,"rotation":-4.440892098500626e-16,"type":"building","subtype":"trenchconnectort2","sortOffset":188,"railPoints":[{"x":0,"y":0,"rotation":3.141592653589793},{"x":169.92424242424204,"y":-104.16666666666653,"rotation":3.141592653589793}],"connections":{"0":{"30":2},"1":{"32":1}}},{"id":34,"x":748.1060606060606,"y":-1693.181818181818,"type":"building","subtype":"trenchconnectort2","sortOffset":188,"railPoints":[{"x":0,"y":0,"rotation":3.141592653589793},{"x":169.9242424242416,"y":104.16666666666656,"rotation":3.141592653589793}],"connections":{"0":{"32":3},"1":{"31":0}}},{"id":35,"x":1904.3560606060623,"y":-3354.8297518119202,"rotation":-1.3322676295501878e-15,"type":"building","subtype":"fortt2","sortOffset":73,"connections":{"1":{"39":3},"2":{"42":0},"3":{"38":0}}},{"id":36,"x":1687.5000000000016,"y":-3137.9736912058597,"rotation":-1.3322676295501878e-15,"type":"building","subtype":"fortt2_atgunait2","sortOffset":51,"connections":{"0":{"41":3}}},{"id":37,"x":2121.212121212123,"y":-3137.9736912058606,"rotation":-1.3322676295501878e-15,"type":"building","subtype":"fortt2_atgunait2","sortOffset":51,"connections":{"0":{"40":0}}},{"id":38,"x":1744.3181818181833,"y":-3354.8297518119202,"rotation":1.5707963267948952,"type":"building","subtype":"fortcornert2","sortOffset":73,"connections":{"0":{"35":3},"6":{"41":6}}},{"id":39,"x":2064.393939393941,"y":-3354.829751811921,"rotation":-1.3322676295501878e-15,"type":"building","subtype":"fortcornert2","sortOffset":73,"connections":{"3":{"35":1},"6":{"40":6}}},{"id":40,"x":2121.212121212123,"y":-3298.011569993739,"rotation":3.1415926535897922,"type":"building","subtype":"fortcornert2","sortOffset":73,"connections":{"0":{"37":0},"3":{"44":3},"6":{"39":6}}},{"id":41,"x":1687.5000000000016,"y":-3298.0115699937382,"rotation":-1.5707963267948983,"type":"building","subtype":"fortcornert2","sortOffset":73,"connections":{"0":{"43":1},"3":{"36":0},"6":{"38":6}}},{"id":42,"x":1904.3560606060623,"y":-3194.7918730240413,"rotation":-1.3322676295501878e-15,"type":"building","subtype":"fortt2_mgait2","sortOffset":51,"connections":{"0":{"35":2},"2":{"59":2}}},{"id":43,"x":1527.4621212121224,"y":-3298.0115699937382,"rotation":-1.7763568394002505e-15,"type":"building","subtype":"fortt2_rifleait2","sortOffset":51,"connections":{"1":{"41":0},"2":{"56":0},"3":{"80":1}}},{"id":44,"x":2281.250000000002,"y":-3298.011569993739,"rotation":-1.3322676295501878e-15,"type":"building","subtype":"fortt2_rifleait2","sortOffset":51,"connections":{"2":{"58":0},"3":{"40":3}}},{"id":45,"x":-2757.5757575757575,"y":-2066.2878787878785,"type":"building","subtype":"fortt2","sortOffset":53,"connections":{"1":{"49":3},"2":{"52":0},"3":{"48":0}}},{"id":46,"x":-2974.431818181818,"y":-1849.431818181818,"type":"building","subtype":"fortt2_atgunait2","sortOffset":36,"connections":{"0":{"51":3}}},{"id":47,"x":-2540.719696969697,"y":-1849.431818181818,"type":"building","subtype":"fortt2_atgunait2","sortOffset":36,"connections":{"0":{"50":0}}},{"id":48,"x":-2917.613636363636,"y":-2066.2878787878785,"rotation":1.5707963267948961,"type":"building","subtype":"fortcornert2","sortOffset":53,"connections":{"0":{"45":3},"6":{"51":6}}},{"id":49,"x":-2597.5378787878785,"y":-2066.2878787878785,"type":"building","subtype":"fortcornert2","sortOffset":53,"connections":{"3":{"45":1},"6":{"50":6}}},{"id":50,"x":-2540.719696969697,"y":-2009.4696969696968,"rotation":3.141592653589793,"type":"building","subtype":"fortcornert2","sortOffset":53,"connections":{"0":{"47":0},"3":{"54":3},"6":{"49":6}}},{"id":51,"x":-2974.431818181818,"y":-2009.4696969696968,"rotation":-1.570796326794897,"type":"building","subtype":"fortcornert2","sortOffset":53,"connections":{"0":{"53":1},"3":{"46":0},"6":{"48":6}}},{"id":52,"x":-2757.5757575757575,"y":-1906.25,"type":"building","subtype":"fortt2_mgait2","sortOffset":36,"connections":{"0":{"45":2},"2":{"86":2}}},{"id":53,"x":-3134.469696969697,"y":-2009.4696969696968,"type":"building","subtype":"fortt2_rifleait2","sortOffset":36,"connections":{"1":{"51":0},"2":{"82":2}}},{"id":54,"x":-2380.681818181818,"y":-2009.4696969696968,"type":"building","subtype":"fortt2_rifleait2","sortOffset":36,"connections":{"2":{"84":2},"3":{"50":3}}},{"id":55,"x":1528.4090909090908,"y":-2843.75,"rotation":-1.3322676295501878e-15,"type":"building","subtype":"trenchempt2","sortOffset":208,"connections":{"0":{"56":1},"2":{"60":1}}},{"id":56,"x":1527.4621212121224,"y":-3218.011569993738,"rotation":1.5707963267948952,"type":"building","subtype":"trenchconnectort2","sortOffset":188,"railPoints":[{"x":0,"y":0,"rotation":3.141592653589793},{"x":214.62121212121193,"y":-0.9469696969695892,"rotation":-3.141592653589793}],"connections":{"0":{"43":2},"1":{"55":0}}},{"id":57,"x":2281.25,"y":-2843.75,"rotation":-1.3322676295501878e-15,"type":"building","subtype":"trenchempt2","sortOffset":209,"connections":{"0":{"58":1},"6":{"61":1}}},{"id":58,"x":2281.250000000002,"y":-3218.0115699937396,"rotation":1.5707963267948952,"type":"building","subtype":"trenchconnectort2","sortOffset":188,"railPoints":[{"x":0,"y":0,"rotation":3.141592653589793},{"x":214.6212121212122,"y":-2.1531598053336368e-13,"rotation":-3.141592653589793}],"connections":{"0":{"44":2},"1":{"57":0}}},{"id":59,"x":1904.3560606060623,"y":-2955.208539690708,"rotation":-1.5707963267948983,"type":"building","subtype":"trencht2","sortOffset":188,"connections":{"1":{"60":0},"2":{"42":2},"3":{"61":0}}},{"id":60,"x":1857.3863636363658,"y":-2955.208539690708,"rotation":3.1415926535897922,"type":"building","subtype":"trenchconnectort2","sortOffset":188,"railPoints":[{"x":0,"y":0,"rotation":3.141592653589793},{"x":168.97727272727448,"y":-111.45853969070733,"rotation":3.141592653589793}],"connections":{"0":{"59":1},"1":{"55":2}}},{"id":61,"x":1951.3257575757596,"y":-2955.208539690708,"rotation":-1.3322676295501878e-15,"type":"building","subtype":"trenchconnectort2","sortOffset":188,"railPoints":[{"x":0,"y":0,"rotation":3.141592653589793},{"x":169.9242424242403,"y":111.4585396907084,"rotation":3.141592653589793}],"connections":{"0":{"59":3},"1":{"57":6}}},{"id":62,"x":73.86363636363636,"y":-2815.340909090909,"rotation":-8.881784197001252e-16,"type":"building","subtype":"trenchempt2","sortOffset":210,"connections":{"7":{"227":1}}},{"id":63,"x":783.1439393939398,"y":-3353.882782114949,"rotation":-1.1102230246251565e-15,"type":"building","subtype":"fortt2","sortOffset":73,"connections":{"1":{"67":3},"2":{"70":0},"3":{"66":0}}},{"id":64,"x":566.2878787878792,"y":-3137.026721508888,"rotation":-1.1102230246251565e-15,"type":"building","subtype":"fortt2_atgunait2","sortOffset":51,"connections":{"0":{"69":3}}},{"id":65,"x":1000.0000000000013,"y":-3137.026721508888,"rotation":-1.1102230246251565e-15,"type":"building","subtype":"fortt2_atgunait2","sortOffset":51,"connections":{"0":{"68":0}}},{"id":66,"x":623.106060606061,"y":-3353.882782114949,"rotation":1.5707963267948954,"type":"building","subtype":"fortcornert2","sortOffset":73,"connections":{"0":{"63":3},"6":{"69":6}}},{"id":67,"x":943.1818181818189,"y":-3353.882782114949,"rotation":-1.1102230246251565e-15,"type":"building","subtype":"fortcornert2","sortOffset":73,"connections":{"3":{"63":1},"6":{"68":6}}},{"id":68,"x":1000.0000000000013,"y":-3297.064600296767,"rotation":3.1415926535897922,"type":"building","subtype":"fortcornert2","sortOffset":73,"connections":{"0":{"65":0},"3":{"72":3},"6":{"67":6}}},{"id":69,"x":566.2878787878792,"y":-3297.064600296767,"rotation":-1.5707963267948981,"type":"building","subtype":"fortcornert2","sortOffset":73,"connections":{"0":{"71":1},"3":{"64":0},"6":{"66":6}}},{"id":70,"x":783.1439393939398,"y":-3193.84490332707,"rotation":-1.1102230246251565e-15,"type":"building","subtype":"fortt2_mgait2","sortOffset":51,"connections":{"0":{"63":2},"2":{"77":2}}},{"id":71,"x":406.2500000000004,"y":-3297.064600296767,"rotation":-1.5543122344752192e-15,"type":"building","subtype":"fortt2_rifleait2","sortOffset":51,"connections":{"1":{"69":0},"2":{"74":0},"3":{"205":1}}},{"id":72,"x":1160.0378787878801,"y":-3297.064600296768,"rotation":-1.1102230246251565e-15,"type":"building","subtype":"fortt2_rifleait2","sortOffset":51,"connections":{"1":{"80":0},"2":{"76":0},"3":{"68":3}}},{"id":73,"x":407.1969696969697,"y":-2842.80303030303,"rotation":-8.881784197001252e-16,"type":"building","subtype":"trenchempt2","sortOffset":206,"connections":{"0":{"74":1},"2":{"78":1}}},{"id":74,"x":406.2500000000004,"y":-3217.0646002967665,"rotation":1.5707963267948954,"type":"building","subtype":"trenchconnectort2","sortOffset":188,"railPoints":[{"x":0,"y":0,"rotation":3.141592653589793},{"x":214.62121212121193,"y":-0.9469696969695892,"rotation":-3.141592653589793}],"connections":{"0":{"71":2},"1":{"73":0}}},{"id":75,"x":1160.0378787878788,"y":-2842.80303030303,"rotation":-8.881784197001252e-16,"type":"building","subtype":"trenchempt2","sortOffset":207,"connections":{"0":{"76":1},"6":{"79":1}}},{"id":76,"x":1160.0378787878801,"y":-3217.0646002967683,"rotation":1.5707963267948954,"type":"building","subtype":"trenchconnectort2","sortOffset":188,"railPoints":[{"x":0,"y":0,"rotation":3.141592653589793},{"x":214.6212121212122,"y":-2.1531598053336368e-13,"rotation":-3.141592653589793}],"connections":{"0":{"72":2},"1":{"75":0}}},{"id":77,"x":783.1439393939406,"y":-2954.2615699937364,"rotation":-1.5707963267948981,"type":"building","subtype":"trencht2","sortOffset":188,"connections":{"1":{"78":0},"2":{"70":2},"3":{"79":0}}},{"id":78,"x":736.1742424242451,"y":-2954.2615699937364,"rotation":3.1415926535897922,"type":"building","subtype":"trenchconnectort2","sortOffset":188,"railPoints":[{"x":0,"y":0,"rotation":3.141592653589793},{"x":168.97727272727622,"y":-111.4585396907054,"rotation":-3.141592653589793}],"connections":{"0":{"77":1},"1":{"73":2}}},{"id":79,"x":830.113636363638,"y":-2954.2615699937364,"rotation":-1.1102230246251565e-15,"type":"building","subtype":"trenchconnectort2","sortOffset":188,"railPoints":[{"x":0,"y":0,"rotation":3.141592653589793},{"x":169.9242424242416,"y":111.4585396907071,"rotation":3.141592653589793}],"connections":{"0":{"77":3},"1":{"75":6}}},{"id":80,"x":1240.0378787878801,"y":-3297.064600296768,"rotation":-1.1102230246251565e-15,"type":"building","subtype":"trenchconnectort2","sortOffset":188,"railPoints":[{"x":0,"y":0,"rotation":3.141592653589793},{"x":207.42424242424215,"y":-0.9469696969696969,"rotation":3.1415926535897922}],"connections":{"0":{"72":1},"1":{"43":3}}},{"id":81,"x":-2757.5757575757575,"y":-1346.590909090909,"type":"building","subtype":"trenchempt2","sortOffset":151,"connections":{"0":{"86":0}}},{"id":82,"x":-3134.469696969697,"y":-1769.8863636363635,"rotation":-1.5707963267948966,"type":"building","subtype":"trencht2","sortOffset":151,"connections":{"0":{"83":1},"2":{"53":2}}},{"id":83,"x":-3134.469696969697,"y":-1562.5,"type":"building","subtype":"trencht2","sortOffset":151,"connections":{"0":{"122":2},"1":{"82":0},"2":{"87":0}}},{"id":84,"x":-2380.681818181818,"y":-1769.8863636363635,"rotation":-1.570796326794897,"type":"building","subtype":"trencht2","sortOffset":151,"connections":{"0":{"85":1},"2":{"54":2}}},{"id":85,"x":-2380.681818181818,"y":-1562.5,"type":"building","subtype":"trencht2","sortOffset":151,"connections":{"0":{"88":1},"1":{"84":0},"2":{"89":6}}},{"id":86,"x":-2757.5757575757575,"y":-1666.6666666666665,"rotation":-1.5707963267948966,"type":"building","subtype":"trencht2","sortOffset":151,"connections":{"0":{"81":0},"1":{"87":1},"2":{"52":2},"3":{"88":0}}},{"id":87,"x":-2974.431818181818,"y":-1562.5,"type":"building","subtype":"trenchconnectort2","sortOffset":151,"railPoints":[{"x":0,"y":0,"rotation":3.141592653589793},{"x":169.9242424242428,"y":-104.16666666666687,"rotation":3.141592653589793}],"connections":{"0":{"83":2},"1":{"86":1}}},{"id":88,"x":-2710.2272727272725,"y":-1666.6666666666665,"type":"building","subtype":"trenchconnectort2","sortOffset":151,"railPoints":[{"x":0,"y":0,"rotation":3.141592653589793},{"x":169.92424242424227,"y":104.16666666666688,"rotation":3.141592653589793}],"connections":{"0":{"86":3},"1":{"85":0}}},{"id":89,"x":-2060.6060606060605,"y":-1562.5,"type":"building","subtype":"trenchempt2","sortOffset":151,"connections":{"1":{"102":0},"6":{"85":2}}},{"id":90,"x":-1925.1893939393938,"y":-2410.9848484848485,"rotation":-0.7853981633974483,"type":"building","subtype":"fortt2","sortOffset":53,"connections":{"1":{"94":3},"2":{"97":0},"3":{"93":0}}},{"id":91,"x":-1925.1893939393938,"y":-2105.1136363636365,"rotation":-0.7853981633974485,"type":"building","subtype":"fortt2_atgunait2","sortOffset":36,"connections":{"0":{"96":3}}},{"id":92,"x":-1619.3181818181818,"y":-2410.9848484848485,"rotation":-0.7853981633974485,"type":"building","subtype":"fortt2_atgunait2","sortOffset":36,"connections":{"0":{"95":0}}},{"id":93,"x":-2037.8787878787878,"y":-2298.2954545454545,"rotation":0.7853981633974483,"type":"building","subtype":"fortcornert2","sortOffset":53,"connections":{"0":{"90":3},"6":{"96":6}}},{"id":94,"x":-1812.5,"y":-2523.6742424242425,"rotation":-0.7853981633974483,"type":"building","subtype":"fortcornert2","sortOffset":53,"connections":{"3":{"90":1},"6":{"95":6}}},{"id":95,"x":-1732.0075757575758,"y":-2523.6742424242425,"rotation":2.356194490192345,"type":"building","subtype":"fortcornert2","sortOffset":53,"connections":{"0":{"92":0},"3":{"99":3},"6":{"94":6}}},{"id":96,"x":-2037.8787878787878,"y":-2217.80303030303,"rotation":-2.356194490192345,"type":"building","subtype":"fortcornert2","sortOffset":53,"connections":{"0":{"98":1},"3":{"91":0},"6":{"93":6}}},{"id":97,"x":-1812.5,"y":-2296.401515151515,"rotation":-0.785398163397448,"type":"building","subtype":"fortt2_mgait2","sortOffset":36,"connections":{"0":{"90":2},"2":{"105":2}}},{"id":98,"x":-2150.5681818181815,"y":-2105.1136363636365,"rotation":-0.7853981633974483,"type":"building","subtype":"fortt2_rifleait2","sortOffset":36,"connections":{"1":{"96":0},"2":{"101":2}}},{"id":99,"x":-1619.3181818181818,"y":-2636.363636363636,"rotation":-0.7853981633974476,"type":"building","subtype":"fortt2_rifleait2","sortOffset":36,"connections":{"2":{"103":2},"3":{"95":3}}},{"id":100,"x":-1416.6666666666665,"y":-1900.5681818181818,"rotation":-0.7853981633974476,"type":"building","subtype":"trenchempt2","sortOffset":151,"connections":{"0":{"105":0}}},{"id":101,"x":-1981.060606060606,"y":-1935.6060606060605,"rotation":-2.356194490192345,"type":"building","subtype":"trencht2","sortOffset":151,"connections":{"0":{"102":1},"2":{"98":2}}},{"id":102,"x":-1834.280303030303,"y":-1788.8257575757575,"rotation":-0.7853981633974483,"type":"building","subtype":"trencht2","sortOffset":151,"connections":{"0":{"89":1},"1":{"101":0},"2":{"106":0}}},{"id":103,"x":-1449.810606060606,"y":-2466.8560606060605,"rotation":-2.3561944901923444,"type":"building","subtype":"trencht2","sortOffset":151,"connections":{"0":{"104":1},"2":{"99":2}}},{"id":104,"x":-1303.030303030303,"y":-2320.0757575757575,"rotation":-0.7853981633974476,"type":"building","subtype":"trencht2","sortOffset":151,"connections":{"0":{"107":1},"1":{"103":0}}},{"id":105,"x":-1642.9924242424242,"y":-2126.8939393939395,"rotation":-2.3561944901923444,"type":"building","subtype":"trencht2","sortOffset":151,"connections":{"0":{"100":0},"1":{"106":1},"2":{"97":2},"3":{"107":0}}},{"id":106,"x":-1722.5378787878788,"y":-1899.621212121212,"rotation":-0.785398163397448,"type":"building","subtype":"trenchconnectort2","sortOffset":151,"railPoints":[{"x":0,"y":0,"rotation":3.141592653589793},{"x":169.9242424242428,"y":-104.16666666666687,"rotation":3.141592653589793}],"connections":{"0":{"102":2},"1":{"105":1}}},{"id":107,"x":-1609.8484848484848,"y":-2160.0378787878785,"rotation":-0.7853981633974476,"type":"building","subtype":"trenchconnectort2","sortOffset":151,"railPoints":[{"x":0,"y":0,"rotation":3.141592653589793},{"x":169.92424242424227,"y":104.16666666666688,"rotation":3.141592653589793}],"connections":{"0":{"105":3},"1":{"104":0}}},{"id":108,"x":-3831.4393939393935,"y":-2066.2878787878785,"type":"building","subtype":"fortt2","sortOffset":53,"connections":{"1":{"112":3},"2":{"115":0},"3":{"111":0}}},{"id":109,"x":-4048.2954545454545,"y":-1849.431818181818,"type":"building","subtype":"fortt2_atgunait2","sortOffset":36,"connections":{"0":{"114":3}}},{"id":110,"x":-3614.583333333333,"y":-1849.431818181818,"type":"building","subtype":"fortt2_atgunait2","sortOffset":36,"connections":{"0":{"113":0}}},{"id":111,"x":-3991.4772727272725,"y":-2066.2878787878785,"rotation":1.5707963267948961,"type":"building","subtype":"fortcornert2","sortOffset":53,"connections":{"0":{"108":3},"6":{"114":6}}},{"id":112,"x":-3671.401515151515,"y":-2066.2878787878785,"type":"building","subtype":"fortcornert2","sortOffset":53,"connections":{"3":{"108":1},"6":{"113":6}}},{"id":113,"x":-3614.583333333333,"y":-2009.4696969696968,"rotation":3.141592653589793,"type":"building","subtype":"fortcornert2","sortOffset":53,"connections":{"0":{"110":0},"3":{"117":3},"6":{"112":6}}},{"id":114,"x":-4048.2954545454545,"y":-2009.4696969696968,"rotation":-1.570796326794897,"type":"building","subtype":"fortcornert2","sortOffset":53,"connections":{"0":{"116":1},"3":{"109":0},"6":{"111":6}}},{"id":115,"x":-3831.4393939393935,"y":-1906.25,"type":"building","subtype":"fortt2_mgait2","sortOffset":36,"connections":{"0":{"108":2},"2":{"123":2}}},{"id":116,"x":-4208.333333333333,"y":-2009.4696969696968,"type":"building","subtype":"fortt2_rifleait2","sortOffset":36,"connections":{"1":{"114":0},"2":{"119":2}}},{"id":117,"x":-3454.5454545454545,"y":-2009.4696969696968,"type":"building","subtype":"fortt2_rifleait2","sortOffset":36,"connections":{"2":{"121":2},"3":{"113":3}}},{"id":118,"x":-3831.4393939393935,"y":-1346.590909090909,"type":"building","subtype":"trenchempt2","sortOffset":151,"connections":{"0":{"123":0}}},{"id":119,"x":-4208.333333333333,"y":-1769.8863636363635,"rotation":-1.5707963267948966,"type":"building","subtype":"trencht2","sortOffset":151,"connections":{"0":{"120":1},"2":{"116":2}}},{"id":120,"x":-4208.333333333333,"y":-1562.5,"type":"building","subtype":"trencht2","sortOffset":151,"connections":{"1":{"119":0},"2":{"124":0}}},{"id":121,"x":-3454.5454545454545,"y":-1769.8863636363635,"rotation":-1.570796326794897,"type":"building","subtype":"trencht2","sortOffset":151,"connections":{"0":{"122":1},"2":{"117":2}}},{"id":122,"x":-3454.5454545454545,"y":-1562.5,"type":"building","subtype":"trencht2","sortOffset":151,"connections":{"0":{"125":1},"1":{"121":0},"2":{"83":0}}},{"id":123,"x":-3831.4393939393935,"y":-1666.6666666666665,"rotation":-1.570796326794897,"type":"building","subtype":"trencht2","sortOffset":151,"connections":{"0":{"118":0},"1":{"124":1},"2":{"115":2},"3":{"125":0}}},{"id":124,"x":-4048.2954545454545,"y":-1562.5,"rotation":-4.440892098500626e-16,"type":"building","subtype":"trenchconnectort2","sortOffset":151,"railPoints":[{"x":0,"y":0,"rotation":3.141592653589793},{"x":169.9242424242428,"y":-104.16666666666687,"rotation":3.141592653589793}],"connections":{"0":{"120":2},"1":{"123":1}}},{"id":125,"x":-3784.090909090909,"y":-1666.6666666666665,"type":"building","subtype":"trenchconnectort2","sortOffset":151,"railPoints":[{"x":0,"y":0,"rotation":3.141592653589793},{"x":169.92424242424227,"y":104.16666666666688,"rotation":3.141592653589793}],"connections":{"0":{"123":3},"1":{"122":0}}},{"id":126,"x":-133.52272727272728,"y":-2438.4469696969695,"rotation":0.7853981633974492,"type":"building","subtype":"fortt2","sortOffset":73,"connections":{"1":{"130":3},"2":{"133":0},"3":{"129":0}}},{"id":127,"x":-439.3939393939394,"y":-2438.4469696969695,"rotation":0.7853981633974492,"type":"building","subtype":"fortt2_atgunait2","sortOffset":51,"connections":{"0":{"132":3}}},{"id":128,"x":-133.52272727272728,"y":-2132.5757575757575,"rotation":0.7853981633974487,"type":"building","subtype":"fortt2_atgunait2","sortOffset":51,"connections":{"0":{"131":0}}},{"id":129,"x":-246.2121212121212,"y":-2551.1363636363635,"rotation":2.3561944901923457,"type":"building","subtype":"fortcornert2","sortOffset":73,"connections":{"0":{"126":3},"6":{"132":6}}},{"id":130,"x":-20.833333333333332,"y":-2325.7575757575755,"rotation":0.7853981633974492,"type":"building","subtype":"fortcornert2","sortOffset":73,"connections":{"3":{"126":1},"6":{"131":6}}},{"id":131,"x":-20.833333333333332,"y":-2245.2651515151515,"rotation":-2.3561944901923444,"type":"building","subtype":"fortcornert2","sortOffset":73,"connections":{"0":{"128":0},"3":{"135":3},"6":{"130":6}}},{"id":132,"x":-326.70454545454544,"y":-2551.1363636363635,"rotation":-0.7853981633974476,"type":"building","subtype":"fortcornert2","sortOffset":73,"connections":{"0":{"134":1},"3":{"127":0},"6":{"129":6}}},{"id":133,"x":-246.2121212121212,"y":-2325.7575757575755,"rotation":0.7853981633974492,"type":"building","subtype":"fortt2_mgait2","sortOffset":51,"connections":{"0":{"126":2},"2":{"140":2}}},{"id":134,"x":-439.3939393939394,"y":-2663.8257575757575,"rotation":0.7853981633974492,"type":"building","subtype":"fortt2_rifleait2","sortOffset":51,"connections":{"1":{"132":0},"2":{"136":2}}},{"id":135,"x":91.8560606060606,"y":-2132.5757575757575,"rotation":0.7853981633974492,"type":"building","subtype":"fortt2_rifleait2","sortOffset":51,"connections":{"2":{"137":2},"3":{"131":3}}},{"id":136,"x":-608.9015151515151,"y":-2494.3181818181815,"rotation":-0.7853981633974474,"type":"building","subtype":"trencht2","sortOffset":188,"connections":{"0":{"138":1},"2":{"134":2}}},{"id":137,"x":-77.65151515151514,"y":-1963.0681818181818,"rotation":-0.7853981633974476,"type":"building","subtype":"trencht2","sortOffset":188,"connections":{"0":{"139":1},"2":{"135":2}}},{"id":138,"x":-755.6818181818181,"y":-2347.5378787878785,"rotation":0.7853981633974492,"type":"building","subtype":"trencht2","sortOffset":188,"connections":{"1":{"136":0},"2":{"141":0}}},{"id":139,"x":-222.53787878787878,"y":-1815.340909090909,"rotation":0.7853981633974492,"type":"building","subtype":"trencht2","sortOffset":188,"connections":{"0":{"142":1},"1":{"137":0},"2":{"17":7}}},{"id":140,"x":-415.71969696969694,"y":-2155.30303030303,"rotation":-0.7853981633974476,"type":"building","subtype":"trencht2","sortOffset":188,"connections":{"1":{"141":1},"2":{"133":2},"3":{"142":0}}},{"id":141,"x":-642.9924242424242,"y":-2234.8484848484845,"rotation":0.7853981633974492,"type":"building","subtype":"trenchconnectort2","sortOffset":188,"railPoints":[{"x":0,"y":0,"rotation":3.141592653589793},{"x":169.92424242424204,"y":-104.16666666666653,"rotation":3.141592653589793}],"connections":{"0":{"138":2},"1":{"140":1}}},{"id":142,"x":-382.57575757575756,"y":-2122.159090909091,"rotation":0.7853981633974492,"type":"building","subtype":"trenchconnectort2","sortOffset":188,"railPoints":[{"x":0,"y":0,"rotation":3.141592653589793},{"x":169.9242424242416,"y":104.16666666666656,"rotation":3.141592653589793}],"connections":{"0":{"140":3},"1":{"139":0}}},{"id":143,"x":-3853.478130506431,"y":-3412.563691611857,"rotation":-1.1102230246251565e-15,"type":"building","subtype":"fortt2","sortOffset":201,"connections":{"1":{"147":3},"2":{"150":0},"3":{"146":0}}},{"id":144,"x":-4070.3341911124908,"y":-3195.7076310057964,"rotation":-1.1102230246251565e-15,"type":"building","subtype":"fortt2_atgunait2","sortOffset":55,"connections":{"0":{"149":3}}},{"id":145,"x":-3636.6220699003707,"y":-3195.707631005797,"rotation":-1.1102230246251565e-15,"type":"building","subtype":"fortt2_atgunait2","sortOffset":55,"connections":{"0":{"148":0}}},{"id":146,"x":-4013.51600929431,"y":-3412.563691611858,"rotation":1.5707963267948954,"type":"building","subtype":"fortcornert2","sortOffset":201,"connections":{"0":{"143":3},"6":{"149":6}}},{"id":147,"x":-3693.4402517185526,"y":-3412.563691611858,"rotation":-1.1102230246251565e-15,"type":"building","subtype":"fortcornert2","sortOffset":201,"connections":{"3":{"143":1},"6":{"148":6}}},{"id":148,"x":-3636.6220699003707,"y":-3355.745509793676,"rotation":3.1415926535897922,"type":"building","subtype":"fortcornert2","sortOffset":201,"connections":{"0":{"145":0},"3":{"152":3},"6":{"147":6}}},{"id":149,"x":-4070.3341911124917,"y":-3355.7455097936754,"rotation":-1.5707963267948981,"type":"building","subtype":"fortcornert2","sortOffset":201,"connections":{"0":{"151":1},"3":{"144":0},"6":{"146":6}}},{"id":150,"x":-3853.478130506431,"y":-3252.525812823978,"rotation":-1.1102230246251565e-15,"type":"building","subtype":"fortt2_mgait2","sortOffset":55,"connections":{"0":{"143":2},"2":{"156":0}}},{"id":151,"x":-4230.372069900371,"y":-3355.745509793675,"rotation":-1.5543122344752192e-15,"type":"building","subtype":"fortt2_rifleait2","sortOffset":55,"connections":{"1":{"149":0}}},{"id":152,"x":-3476.5841911124917,"y":-3355.7455097936763,"rotation":-1.1102230246251565e-15,"type":"building","subtype":"fortt2_rifleait2","sortOffset":55,"connections":{"1":{"172":0},"3":{"148":3}}},{"id":153,"x":-3853.180237465937,"y":-2852.066673951596,"rotation":-8.881784197001252e-16,"type":"building","subtype":"trenchempt2","sortOffset":201,"connections":{"0":{"156":1},"2":{"155":6},"6":{"154":2}}},{"id":154,"x":-4173.255995041694,"y":-2852.066673951596,"rotation":-1.133107779529596e-15,"type":"building","subtype":"trenchempt2","sortOffset":201,"connections":{"2":{"153":6}}},{"id":155,"x":-3533.1044798901794,"y":-2852.066673951596,"rotation":-8.881784197001252e-16,"type":"building","subtype":"trenchempt2","sortOffset":201,"connections":{"2":{"224":0},"6":{"153":2}}},{"id":156,"x":-3853.4781305064303,"y":-3172.5258128239775,"rotation":1.5707963267948954,"type":"building","subtype":"trenchconnectort2","sortOffset":195,"railPoints":[{"x":0,"y":0,"rotation":3.141592653589793},{"x":160.21117630256236,"y":-0.13541872680762748,"rotation":-3.141592653589793}],"connections":{"0":{"150":2},"1":{"153":0}}},{"id":157,"x":-2797.646377888979,"y":-3409.928835842081,"rotation":-1.1102230246251565e-15,"type":"building","subtype":"fortt2","sortOffset":65,"connections":{"1":{"161":3},"2":{"164":0},"3":{"160":0}}},{"id":158,"x":-3014.5024384950398,"y":-3193.0727752360212,"rotation":-1.1102230246251565e-15,"type":"building","subtype":"fortt2_atgunait2","sortOffset":48,"connections":{"0":{"163":3}}},{"id":159,"x":-2580.7903172829183,"y":-3193.0727752360217,"rotation":-1.1102230246251565e-15,"type":"building","subtype":"fortt2_atgunait2","sortOffset":48,"connections":{"0":{"162":0}}},{"id":160,"x":-2957.684256676858,"y":-3409.928835842081,"rotation":1.5707963267948954,"type":"building","subtype":"fortcornert2","sortOffset":65,"connections":{"0":{"157":3},"6":{"163":6}}},{"id":161,"x":-2637.6084991011003,"y":-3409.928835842081,"rotation":-1.1102230246251565e-15,"type":"building","subtype":"fortcornert2","sortOffset":65,"connections":{"3":{"157":1},"6":{"162":6}}},{"id":162,"x":-2580.7903172829183,"y":-3353.1106540239007,"rotation":3.1415926535897922,"type":"building","subtype":"fortcornert2","sortOffset":65,"connections":{"0":{"159":0},"3":{"166":3},"6":{"161":6}}},{"id":163,"x":-3014.5024384950398,"y":-3353.1106540239,"rotation":-1.5707963267948981,"type":"building","subtype":"fortcornert2","sortOffset":65,"connections":{"0":{"165":1},"3":{"158":0},"6":{"160":6}}},{"id":164,"x":-2797.646377888979,"y":-3249.8909570542028,"rotation":-1.1102230246251565e-15,"type":"building","subtype":"fortt2_mgait2","sortOffset":48,"connections":{"0":{"157":2},"2":{"170":0}}},{"id":165,"x":-3174.5403172829183,"y":-3353.1106540238993,"rotation":-1.5543122344752192e-15,"type":"building","subtype":"fortt2_rifleait2","sortOffset":48,"connections":{"1":{"163":0},"3":{"172":1}}},{"id":166,"x":-2420.7524384950398,"y":-3353.1106540239007,"rotation":-1.1102230246251565e-15,"type":"building","subtype":"fortt2_rifleait2","sortOffset":48,"connections":{"1":{"187":0},"3":{"162":3}}},{"id":167,"x":-2797.3484848484845,"y":-2849.431818181818,"rotation":-8.881784197001252e-16,"type":"building","subtype":"trenchempt2","sortOffset":198,"connections":{"0":{"170":1},"2":{"169":6},"6":{"168":2}}},{"id":168,"x":-3117.4242424242425,"y":-2849.431818181818,"rotation":-1.133107779529596e-15,"type":"building","subtype":"trenchempt2","sortOffset":200,"connections":{"2":{"167":6},"6":{"224":1}}},{"id":169,"x":-2477.272727272727,"y":-2849.431818181818,"rotation":-8.881784197001252e-16,"type":"building","subtype":"trenchempt2","sortOffset":199,"connections":{"2":{"225":0},"6":{"167":2}}},{"id":170,"x":-2797.646377888979,"y":-3169.8909570542023,"rotation":1.5707963267948954,"type":"building","subtype":"trenchconnectort2","sortOffset":183,"railPoints":[{"x":0,"y":0,"rotation":3.141592653589793},{"x":160.21117630256236,"y":-0.13541872680762748,"rotation":-3.141592653589793}],"connections":{"0":{"164":2},"1":{"167":0}}},{"id":171,"x":-2080.492424242424,"y":-2849.431818181818,"rotation":-0.7853981633974492,"type":"building","subtype":"trenchempt2","sortOffset":202,"connections":{"2":{"226":0},"7":{"225":1}}},{"id":172,"x":-3396.5841911124917,"y":-3355.7455097936763,"rotation":-8.881784197001252e-16,"type":"building","subtype":"trenchconnectort2","sortOffset":196,"railPoints":[{"x":0,"y":0,"rotation":3.141592653589793},{"x":142.04387382957302,"y":2.63485576977815,"rotation":3.1415926535897922}],"connections":{"0":{"152":1},"1":{"165":3}}},{"id":173,"x":-1952.504309383079,"y":-3762.796628152787,"rotation":-0.7853981633974494,"type":"building","subtype":"fortt2","sortOffset":65,"connections":{"1":{"177":3},"2":{"180":0},"3":{"176":0}}},{"id":174,"x":-1952.50430938308,"y":-3456.115846160896,"rotation":-0.7853981633974494,"type":"building","subtype":"fortt2_atgunait2","sortOffset":48,"connections":{"0":{"179":3}}},{"id":175,"x":-1645.8235273911873,"y":-3762.7966281527893,"rotation":-0.7853981633974494,"type":"building","subtype":"fortt2_atgunait2","sortOffset":48,"connections":{"0":{"178":0}}},{"id":176,"x":-2065.668178720698,"y":-3649.632758815167,"rotation":0.7853981633974472,"type":"building","subtype":"fortcornert2","sortOffset":65,"connections":{"0":{"173":3},"6":{"179":6}}},{"id":177,"x":-1839.3404400454597,"y":-3875.9604974904078,"rotation":-0.7853981633974494,"type":"building","subtype":"fortcornert2","sortOffset":65,"connections":{"3":{"173":1},"6":{"178":6}}},{"id":178,"x":-1758.9873967288067,"y":-3875.9604974904078,"rotation":2.356194490192344,"type":"building","subtype":"fortcornert2","sortOffset":65,"connections":{"0":{"175":0},"3":{"182":3},"6":{"177":6}}},{"id":179,"x":-2065.668178720699,"y":-3569.279715498514,"rotation":-2.3561944901923466,"type":"building","subtype":"fortcornert2","sortOffset":65,"connections":{"0":{"181":1},"3":{"174":0},"6":{"176":6}}},{"id":180,"x":-1839.3404400454594,"y":-3649.6327588151694,"rotation":-0.7853981633974494,"type":"building","subtype":"fortt2_mgait2","sortOffset":48,"connections":{"0":{"173":2},"2":{"186":0}}},{"id":181,"x":-2178.8320480583193,"y":-3456.1158461608943,"rotation":-0.7853981633974499,"type":"building","subtype":"fortt2_rifleait2","sortOffset":48,"connections":{"1":{"179":0},"3":{"187":1}}},{"id":182,"x":-1645.8235273911876,"y":-3989.124366828028,"rotation":-0.7853981633974494,"type":"building","subtype":"fortt2_rifleait2","sortOffset":48,"connections":{"3":{"178":3}}},{"id":183,"x":-1555.871212121212,"y":-3366.4772727272725,"rotation":-0.7853981633974492,"type":"building","subtype":"trenchempt2","sortOffset":195,"connections":{"0":{"186":1},"2":{"185":6},"6":{"184":2}}},{"id":184,"x":-1782.1969696969695,"y":-3140.151515151515,"rotation":-0.7853981633974494,"type":"building","subtype":"trenchempt2","sortOffset":196,"connections":{"2":{"183":6},"6":{"226":1}}},{"id":185,"x":-1329.5454545454545,"y":-3592.80303030303,"rotation":-0.7853981633974492,"type":"building","subtype":"trenchempt2","sortOffset":197,"connections":{"6":{"183":2}}},{"id":186,"x":-1782.7718975505347,"y":-3593.0642163202438,"rotation":0.7853981633974472,"type":"building","subtype":"trenchconnectort2","sortOffset":183,"railPoints":[{"x":0,"y":0,"rotation":3.141592653589793},{"x":160.21117630256236,"y":-0.13541872680762748,"rotation":-3.141592653589793}],"connections":{"0":{"180":2},"1":{"183":0}}},{"id":187,"x":-2340.7524384950393,"y":-3353.1106540239,"rotation":-1.1102230246251565e-15,"type":"building","subtype":"trenchconnectort2","sortOffset":183,"railPoints":[{"x":0,"y":0,"rotation":3.141592653589793},{"x":105.35184794179676,"y":-46.436649642068815,"rotation":2.3561944901923444}],"connections":{"0":{"166":1},"1":{"181":3}}},{"id":188,"x":-110.84864556567754,"y":-3723.9593238830744,"rotation":0.7853981633974474,"type":"building","subtype":"fortt2","sortOffset":73,"connections":{"1":{"192":3},"2":{"195":0},"3":{"191":0}}},{"id":189,"x":-417.5294275575703,"y":-3723.9593238830753,"rotation":0.7853981633974474,"type":"building","subtype":"fortt2_atgunait2","sortOffset":51,"connections":{"0":{"194":3}}},{"id":190,"x":-110.84864556567754,"y":-3417.2785418911817,"rotation":0.7853981633974474,"type":"building","subtype":"fortt2_atgunait2","sortOffset":51,"connections":{"0":{"193":0}}},{"id":191,"x":-224.01251490329742,"y":-3837.1231932206942,"rotation":2.356194490192344,"type":"building","subtype":"fortcornert2","sortOffset":73,"connections":{"0":{"188":3},"6":{"194":6}}},{"id":192,"x":2.3152237719415756,"y":-3610.7954545454563,"rotation":0.7853981633974474,"type":"building","subtype":"fortcornert2","sortOffset":73,"connections":{"3":{"188":1},"6":{"193":6}}},{"id":193,"x":2.3152237719424367,"y":-3530.4424112288025,"rotation":-2.3561944901923457,"type":"building","subtype":"fortcornert2","sortOffset":73,"connections":{"0":{"190":0},"3":{"197":3},"6":{"192":6}}},{"id":194,"x":-304.36555821994943,"y":-3837.1231932206942,"rotation":-0.785398163397449,"type":"building","subtype":"fortcornert2","sortOffset":73,"connections":{"0":{"196":1},"3":{"189":0},"6":{"191":6}}},{"id":195,"x":-224.01251490329753,"y":-3610.7954545454554,"rotation":0.7853981633974474,"type":"building","subtype":"fortt2_mgait2","sortOffset":51,"connections":{"0":{"188":2},"2":{"202":2}}},{"id":196,"x":-417.5294275575703,"y":-3950.287062558314,"rotation":0.7853981633974468,"type":"building","subtype":"fortt2_rifleait2","sortOffset":51,"connections":{"1":{"194":0},"2":{"199":0}}},{"id":197,"x":115.47909310956241,"y":-3417.278541891182,"rotation":0.7853981633974474,"type":"building","subtype":"fortt2_rifleait2","sortOffset":51,"connections":{"1":{"205":0},"2":{"201":0},"3":{"193":3}}},{"id":198,"x":-738.6363636363636,"y":-3627.840909090909,"rotation":0.7853981633974474,"type":"building","subtype":"trenchempt2","sortOffset":205,"connections":{"0":{"199":1},"2":{"203":1}}},{"id":199,"x":-474.09797005249493,"y":-3893.7185200633903,"rotation":2.356194490192344,"type":"building","subtype":"trenchconnectort2","sortOffset":188,"railPoints":[{"x":0,"y":0,"rotation":3.141592653589793},{"x":214.62121212121193,"y":-0.9469696969695892,"rotation":-3.141592653589793}],"connections":{"0":{"196":2},"1":{"198":0}}},{"id":200,"x":-206.43939393939394,"y":-3095.643939393939,"rotation":0.7853981633974474,"type":"building","subtype":"trenchempt2","sortOffset":204,"connections":{"0":{"201":1},"2":{"227":0},"6":{"204":1}}},{"id":201,"x":58.91055061463864,"y":-3360.7099993962584,"rotation":2.356194490192344,"type":"building","subtype":"trenchconnectort2","sortOffset":188,"railPoints":[{"x":0,"y":0,"rotation":3.141592653589793},{"x":214.6212121212122,"y":-2.1531598053336368e-13,"rotation":-3.141592653589793}],"connections":{"0":{"197":2},"1":{"200":0}}},{"id":202,"x":-393.4235145625739,"y":-3441.384454886178,"rotation":-0.785398163397449,"type":"building","subtype":"trencht2","sortOffset":188,"connections":{"1":{"203":0},"2":{"195":2},"3":{"204":0}}},{"id":203,"x":-426.63610580012306,"y":-3474.597046123727,"rotation":-2.3561944901923457,"type":"building","subtype":"trenchconnectort2","sortOffset":188,"railPoints":[{"x":0,"y":0,"rotation":3.141592653589793},{"x":168.9772727272736,"y":-112.25772336863969,"rotation":3.141592653589793}],"connections":{"0":{"202":1},"1":{"198":2}}},{"id":204,"x":-360.21092332502303,"y":-3408.171863648627,"rotation":0.7853981633974474,"type":"building","subtype":"trenchconnectort2","sortOffset":188,"railPoints":[{"x":0,"y":0,"rotation":3.141592653589793},{"x":169.72350573265018,"y":112.2577233686399,"rotation":3.141592653589793}],"connections":{"0":{"202":3},"1":{"200":6}}},{"id":205,"x":172.04763560448671,"y":-3360.7099993962584,"rotation":0.7853981633974474,"type":"building","subtype":"trenchconnectort2","sortOffset":188,"railPoints":[{"x":0,"y":0,"rotation":3.141592653589793},{"x":154.04163083364176,"y":-64.03344424449224,"rotation":2.356194490192344}],"connections":{"0":{"197":1},"1":{"71":3}}},{"id":206,"x":-3445.0757575757575,"y":-4281.25,"type":"building","subtype":"fortt2_mgait2","sortOffset":54,"connections":{"2":{"214":0}}},{"id":207,"x":-2964.962121212121,"y":-4281.25,"type":"building","subtype":"fortt2_mgait2","sortOffset":54,"connections":{"2":{"208":0}}},{"id":208,"x":-2964.9621212121206,"y":-4201.25,"rotation":1.5707963267948966,"type":"building","subtype":"trenchconnectort2","sortOffset":193,"railPoints":[{"x":0,"y":0,"rotation":3.141592653589793},{"x":160.07575757575754,"y":0,"rotation":-3.141592653589793}],"connections":{"0":{"207":2},"1":{"216":0}}},{"id":209,"x":-2484.8484848484845,"y":-4281.25,"type":"building","subtype":"fortt2_mgait2","sortOffset":54,"connections":{"2":{"210":0}}},{"id":210,"x":-2484.848484848484,"y":-4201.25,"rotation":1.5707963267948966,"type":"building","subtype":"trenchconnectort2","sortOffset":193,"railPoints":[{"x":0,"y":0,"rotation":3.141592653589793},{"x":160.07575757575754,"y":0,"rotation":-3.141592653589793}],"connections":{"0":{"209":2},"1":{"211":0}}},{"id":211,"x":-2484.8484848484845,"y":-3881.6287878787875,"type":"building","subtype":"trenchempt2","sortOffset":193,"connections":{"0":{"210":1}}},{"id":212,"x":312.5000000000001,"y":-4059.6590909090905,"type":"building","subtype":"fortt2_atgunait2","sortOffset":53,"connections":{"2":{"213":0}}},{"id":213,"x":312.5000000000001,"y":-3899.621212121212,"type":"building","subtype":"fortcornert1","sortOffset":80,"connections":{"0":{"212":2},"6":{"217":0}}},{"id":214,"x":-3445.0757575757575,"y":-4121.212121212121,"type":"building","subtype":"fortt1","sortOffset":81,"connections":{"0":{"206":2},"2":{"215":0}}},{"id":215,"x":-3445.0757575757575,"y":-3961.174242424242,"type":"building","subtype":"fortt1","sortOffset":81,"connections":{"0":{"214":2}}},{"id":216,"x":-2964.962121212121,"y":-3961.174242424242,"type":"building","subtype":"fortt1","sortOffset":81,"connections":{"0":{"208":1}}},{"id":217,"x":397.7272727272728,"y":-3814.393939393939,"rotation":-0.7853981633974485,"type":"building","subtype":"fortt1","sortOffset":80,"connections":{"0":{"213":6}}},{"id":218,"x":791.6666666666666,"y":-4059.6590909090905,"type":"building","subtype":"fortt2_atgunait2","sortOffset":53,"connections":{"2":{"219":0}}},{"id":219,"x":791.6666666666666,"y":-3979.659090909091,"rotation":1.5707963267948966,"type":"building","subtype":"trenchconnectort2","sortOffset":192,"railPoints":[{"x":0,"y":0,"rotation":3.141592653589793},{"x":108.69660902022798,"y":-28.658730232348947,"rotation":2.356194490192345}],"connections":{"0":{"218":2},"1":{"220":0}}},{"id":220,"x":876.8939393939394,"y":-3814.393939393939,"rotation":-0.7853981633974485,"type":"building","subtype":"fortt1","sortOffset":80,"connections":{"0":{"219":1}}},{"id":221,"x":1270.8333333333333,"y":-4059.6590909090905,"type":"building","subtype":"fortt2_atgunait2","sortOffset":53,"connections":{"2":{"222":0}}},{"id":222,"x":1270.8333333333333,"y":-3979.659090909091,"rotation":1.5707963267948966,"type":"building","subtype":"trenchconnectort2","sortOffset":192,"railPoints":[{"x":0,"y":0,"rotation":3.141592653589793},{"x":108.69660902022798,"y":-28.658730232348947,"rotation":2.356194490192345}],"connections":{"0":{"221":2},"1":{"223":7}}},{"id":223,"x":1412.8787878787878,"y":-3757.5757575757575,"type":"building","subtype":"trenchempt2","sortOffset":211,"connections":{"7":{"222":1}}},{"id":224,"x":-3373.1044798901785,"y":-2852.066673951596,"rotation":-8.881784197001252e-16,"type":"building","subtype":"trenchconnectort2","sortOffset":197,"railPoints":[{"x":0,"y":0,"rotation":3.141592653589793},{"x":95.68023746593683,"y":2.6348557697790116,"rotation":3.141592653589793}],"connections":{"0":{"155":2},"1":{"168":6}}},{"id":225,"x":-2317.2727272727266,"y":-2849.431818181818,"rotation":-8.881784197001252e-16,"type":"building","subtype":"trenchconnectort2","sortOffset":198,"railPoints":[{"x":0,"y":0,"rotation":3.141592653589793},{"x":77.18771790580867,"y":0,"rotation":3.141592653589793}],"connections":{"0":{"169":2},"1":{"171":7}}},{"id":226,"x":-1967.3553392525762,"y":-2962.5689031716656,"rotation":-0.7853981633974492,"type":"building","subtype":"trenchconnectort2","sortOffset":199,"railPoints":[{"x":0,"y":0,"rotation":3.141592653589793},{"x":96.49660785798577,"y":5.3568695544444465,"rotation":3.141592653589793}],"connections":{"0":{"171":2},"1":{"184":6}}},{"id":227,"x":-93.30230894954627,"y":-2982.5068544040923,"rotation":0.7853981633974474,"type":"building","subtype":"trenchconnectort2","sortOffset":200,"railPoints":[{"x":0,"y":0,"rotation":3.141592653589793},{"x":76.94439706649759,"y":0,"rotation":3.141592653589793}],"connections":{"0":{"200":2},"1":{"62":7}}}],"version":"1.0.2"}