{"projectSettings":{"showProductionIcons":true,"showRangeWhenSelected":true,"ranges":{"crane":false,"radio":false,"killbox":false,"killboxMG":false,"killboxAT":false,"killboxArty":false}},"entities":[{"id":62,"x":4454.545454545454,"y":5196.969696969697,"rotation":2.356194490192345,"type":"building","subtype":"fortcornert3","sortOffset":39,"connections":{"0":{"65":0},"6":{"64":3}}},{"id":63,"x":4214.015151515151,"y":5196.969696969697,"rotation":-0.7853981633974485,"type":"building","subtype":"fortcornert3","sortOffset":42,"connections":{"3":{"67":1},"6":{"64":1}}},{"id":64,"x":4334.280303030303,"y":5196.969696969697,"rotation":3.141592653589793,"type":"building","subtype":"fortt3_atgunait3","sortOffset":41,"connections":{"1":{"63":6},"3":{"62":6}}},{"id":65,"x":4567.234848484848,"y":5309.659090909091,"rotation":-0.7853981633974485,"type":"building","subtype":"fortt3_rifleait3","sortOffset":43,"connections":{"0":{"62":0},"3":{"69":3}}},{"id":67,"x":4101.325757575757,"y":5309.659090909091,"rotation":-0.7853981633974485,"type":"building","subtype":"fortt3_rifleait3","sortOffset":44,"connections":{"1":{"63":3},"2":{"68":0}}},{"id":68,"x":4214.015151515151,"y":5422.348484848485,"rotation":-0.7853981633974485,"type":"building","subtype":"fortcornert3","sortOffset":45,"connections":{"0":{"67":2},"3":{"73":0},"6":{"75":1}}},{"id":69,"x":4454.545454545454,"y":5422.348484848485,"rotation":2.356194490192345,"type":"building","subtype":"fortcornert3","sortOffset":46,"connections":{"0":{"72":0},"3":{"65":3},"6":{"75":3}}},{"id":70,"x":4214.015151515151,"y":5647.727272727272,"rotation":-0.7853981633974485,"type":"building","subtype":"fortcornert3","sortOffset":52,"connections":{"0":{"73":1},"6":{"74":3}}},{"id":71,"x":4454.545454545454,"y":5647.727272727272,"rotation":2.356194490192345,"type":"building","subtype":"fortcornert3","sortOffset":50,"connections":{"3":{"72":3},"6":{"74":1}}},{"id":72,"x":4567.234848484848,"y":5535.037878787879,"rotation":-0.7853981633974483,"type":"building","subtype":"fortt3_atgunait3","sortOffset":49,"connections":{"0":{"69":0},"3":{"71":3}}},{"id":73,"x":4101.325757575757,"y":5535.037878787879,"rotation":0.7853981633974483,"type":"building","subtype":"fortt3_atgunait3","sortOffset":51,"connections":{"0":{"68":3},"1":{"70":0}}},{"id":74,"x":4334.280303030303,"y":5647.727272727272,"type":"building","subtype":"fortt3_rifleait3","sortOffset":53,"connections":{"1":{"71":6},"3":{"70":6}}},{"id":75,"x":4334.280303030303,"y":5422.348484848485,"rotation":3.141592653589793,"type":"building","subtype":"fortt3_artilleryait3","sortOffset":54,"connections":{"1":{"68":6},"3":{"69":6}}}],"version":"1.0.2"}